{
  "categories": {
    "level1": {
      "name": "一级敏感词（轻度）",
      "description": "个人信息、账号等，检测到用*代替",
      "words": [
        "个人信息",
        "身份证",
        "银行卡",
        "密码",
        "账号",
        "手机号",
        "电话号码",
        "邮箱",
        "地址",
        "QQ号",
        "微信号",
        "支付宝",
        "微信支付"
      ]
    },
    "level2": {
      "name": "二级敏感词（中度）",
      "description": "其他违法行为，以及自杀、自残等对用户有人身危险行为，打*并提交管理员审核",
      "words": [
        "诈骗电话",
        "虚假广告",
        "假冒",
        "盗版",
        "侵权",
        "自杀",
        "自残",
        "打架",
        "斗殴",
        "赌博",
        "赌场",
        "赌钱",
        "六合彩",
        "时时彩",
        "彩票",
        "黑客",
        "病毒",
        "黑客攻击",
        "网络攻击",
        "傻逼",
        "SB",
        "疯狗"
      ]
    },
    "level3": {
      "name": "三级敏感词（严重）",
      "description": "最严重的敏感内容，如色情、暴力、政治敏感、毒品、严重违法行为等",
      "words": [
        "操",
        "操你",
        "操逼",
        "78",
        "91",
        "妈逼",
        "妈死",
        "爸死",
        "爷死",
        "奶死",
        "全家死",
        "死妈",
        "死爸",
        "死爷",
        "死奶",
        "死全家",
        "变态",
        "鸡巴",
        "口交",
        "给我口",
        "色情",
        "情色",
        "黄色",
        "淫秽",
        "约炮",
        " porn",
        "做爱",
        "SM",
        "抖M",
        "调教",
        "榨精",
        "性交",
        "性行为",
        "性器官",
        "乳房",
        "阴茎",
        "阴道",
        "强奸",
        "轮奸",
        "卖淫",
        "嫖娼",
        "招妓",
        "援交",
        "露点",
        "裸照",
        "三级片",
        "AV女优",
        "暴力",
        "杀人",
        "谋杀",
        "流血",
        "死亡",
        "血腥",
        "恐怖",
        "爆炸",
        "枪击",
        "刀砍",
        "政治",
        "台独",
        "藏独",
        "政府",
        "共产党",
        "国务院",
        "民主",
        "自由",
        "抗议",
        "示威",
        "游行",
        "罢工",
        "颠覆",
        "叛乱",
        "毒品",
        "大麻",
        "海洛因",
        "冰毒",
        "摇头丸",
        "吸毒",
        "贩毒",
        "诈骗",
        "骗钱",
        "传销",
        "非法集资",
        "网络诈骗",
        "盗窃",
        "抢劫",
        "绑架",
        "敲诈勒索",
        "黄色网站",
        "赌博网站",
        "毒品网站",
        "违法网站"
      ]
    }
  }
}